wdcmd/__init__.py
wdcmd/wdcmd_args_parse.py
wdcmd/wdcmd_cmd_config.py
wdcmd/wdcmd_context.py
wdcmd/wdcmd_core.py
wdcmd/wdcmd_interface.py
wd_pytools-0.0.3.dist-info/LICENSE
wd_pytools-0.0.3.dist-info/METADATA
wd_pytools-0.0.3.dist-info/WHEEL
wd_pytools-0.0.3.dist-info/top_level.txt
wd_pytools-0.0.3.dist-info/RECORD
