Metadata-Version: 2.1
Name: wd-pytools
Version: 0.0.3
Summary: This is the tools for python.
Home-page: http://pypi.org
Author: teshin
Author-email: 1443965173@qq.com
Classifier: License :: OSI Approved :: MIT License
Classifier: Intended Audience :: Developers
Classifier: Operating System :: OS Independent
Classifier: Programming Language :: Python
Classifier: Programming Language :: Python :: 3.10
License-File: LICENSE
